{
    "builders": [
        {
            "type": "yandex",
            "service_account_key_file": "/home/admins/otus/secrets/key.json",
            "folder_id": "b1g9rbhfq6ba8dfpgv37",
            "subnet_id": "e9bmh97l31novt99ndqb",
            "zone":     "ru-central1-a",
            "use_ipv4_nat":     true,
            "source_image_family": "ubuntu-1604-lts",
            "image_name": "reddit-full-{{timestamp}}",
            "image_family": "reddit-full",
            "ssh_username": "ubuntu",
            "platform_id": "standard-v1",
	    "disk_size_gb": "10"
        }
    ],
    "provisioners": [
        {
            "type": "shell",
            "inline": [
                "echo Waiting for apt-get to finish...",
                "a=1; while [ -n \"$(pgrep apt-get)\" ]; do echo $a; sleep 1s; a=$(expr $a + 1); done",
                "echo Done."
            ]
        },
        {
            "type": "shell",
            "script": "scripts/install_ruby.sh",
            "execute_command": "sudo {{.Path}}"
        },
        {
            "type": "shell",
            "script": "scripts/install_mongodb.sh",
            "execute_command": "sudo {{.Path}}"
        },
        {
            "type": "shell",
            "script": "scripts/install_reddit.sh",
            "execute_command": "sudo {{.Path}}"
        },
	{
            "type": "file",
            "source": "files/puma.service",
            "destination": "/tmp/puma.service"
        },
	{
	    "type": "shell",
	    "inline": [
	    "sudo mv /tmp/puma.service /etc/systemd/system/puma.service",
	    "sudo systemctl daemon-reload",
	    "sudo systemctl enable puma",
	    "sudo systemctl start puma"]
	}
	]
}
